epmux/README.md
epmux/__init__.py
epmux/epmux.py
epmux/epmux-darwin/libepmux.dylib
epmux/epmux-debian/libepmux.so
epmux/epmux-win32/epmux.dll
epmux/epmux-win64/epmux.dll
epmux-1.0.0.dist-info/METADATA
epmux-1.0.0.dist-info/WHEEL
epmux-1.0.0.dist-info/entry_points.txt
epmux-1.0.0.dist-info/license_files/LICENSE
epmux-1.0.0.dist-info/RECORD
